foliumEllipsis/__init__.py
foliumEllipsis/util.py
foliumEllipsis-0.0.6.dist-info/LICENSE
foliumEllipsis-0.0.6.dist-info/METADATA
foliumEllipsis-0.0.6.dist-info/WHEEL
foliumEllipsis-0.0.6.dist-info/top_level.txt
foliumEllipsis-0.0.6.dist-info/RECORD
