Metadata-Version: 2.1
Name: foliumEllipsis
Version: 0.0.6
Summary: Package to add Ellipsis Drive layers to folium
Home-page: https://github.com/ellipsis-drive/folium
Author: Daniel van der Maas
Author-email: daniel@ellipsis-drive.com
Classifier: Programming Language :: Python :: 3
Classifier: License :: OSI Approved :: MIT License
Classifier: Operating System :: OS Independent
Requires-Python: >=3.6
License-File: LICENSE
Requires-Dist: folium
Requires-Dist: folium-vectorgrid
